spaTyper/__init__.py
spaTyper/enricher.py
spaTyper/spa_typing.py
spaTyper/utils.py
spaTyper-0.3.3.data/scripts/spaTyper
spaTyper-0.3.3.data/scripts/sparepeats.fasta
spaTyper-0.3.3.data/scripts/spatypes.txt
spaTyper-0.3.3.dist-info/LICENSE
spaTyper-0.3.3.dist-info/METADATA
spaTyper-0.3.3.dist-info/WHEEL
spaTyper-0.3.3.dist-info/top_level.txt
spaTyper-0.3.3.dist-info/RECORD
