Metadata-Version: 2.1
Name: spaTyper
Version: 0.3.3
Summary: Typing of Staphylococcus aureus protein A from assemblies
Home-page: https://github.com/JFsanchezherrero/spa_typing
Author: Mitchell Sullivan; Jose F. Sanchez-Herrero
Author-email: jfbioinformatics@gmail.com
License: GPLv3
Platform: UNKNOWN
Classifier: Programming Language :: Python :: 3
Classifier: License :: OSI Approved :: GNU Lesser General Public License v3 (LGPLv3)
Classifier: Operating System :: OS Independent
